MANIFEST.in
README.md
VERSION
setup.py
aerender/__init__.py
aerender/exceptions.py
aerender/wrapper.py
aerender.egg-info/PKG-INFO
aerender.egg-info/SOURCES.txt
aerender.egg-info/dependency_links.txt
aerender.egg-info/top_level.txt
test/__init__.py
test/test_wrapper.py