Metadata-Version: 2.1
Name: aerender
Version: 0.1.2
Summary: asyncio wrapper for Adobe After Effects aerender
Home-page: https://github.com/devtud/aerender
Author: devtud
Author-email: devtud@gmail.com
License: UNKNOWN
Project-URL: Source, https://github.com/devtud/aerender
Keywords: asyncio async aerender
Platform: UNKNOWN
Classifier: Development Status :: 3 - Alpha
Classifier: Intended Audience :: Developers
Classifier: Topic :: Software Development :: Build Tools
Classifier: License :: OSI Approved :: MIT License
Classifier: Programming Language :: Python :: 3.7
Requires-Python: >=3.7, <4
